pywigxjpf_ffi.pyd
pywigxjpf/__init__.py
pywigxjpf/pywigxjpf.py
pywigxjpf/pywigxjpf_ffi_builder.py
pywigxjpf_win-1.11.dist-info/COPYING
pywigxjpf_win-1.11.dist-info/COPYING.LESSER
pywigxjpf_win-1.11.dist-info/METADATA
pywigxjpf_win-1.11.dist-info/WHEEL
pywigxjpf_win-1.11.dist-info/top_level.txt
pywigxjpf_win-1.11.dist-info/RECORD
