Metadata-Version: 2.1
Name: pywigxjpf-win
Version: 1.11
Summary: Windows binary wheels for pywigxjpf
Home-page: http://fy.chalmers.se/subatom/wigxjpf
Author: C. Forssen and H. T. Johansson
License: GPLv3
Platform: UNKNOWN
